HMF/__init__.py
HMF/constants.py
HMF/core.py
HMF/hmf.py
HMF/parallel.py
HMF/utils.py
hierarchical_memmap_format-0.0b45.dist-info/LICENSE
hierarchical_memmap_format-0.0b45.dist-info/METADATA
hierarchical_memmap_format-0.0b45.dist-info/WHEEL
hierarchical_memmap_format-0.0b45.dist-info/top_level.txt
hierarchical_memmap_format-0.0b45.dist-info/RECORD
